stream_connect/__init__.py
stream_connect/commons.py
stream_connect/connector.py
stream_connect/errors.py
stream_connect/test.py
stream_connect/services/___init__.py
stream_connect/services/base.py
stream_connect/services/kafka.py
stream_connect/services/response.py
stream_connect-1.0.8.dist-info/METADATA
stream_connect-1.0.8.dist-info/WHEEL
stream_connect-1.0.8.dist-info/top_level.txt
stream_connect-1.0.8.dist-info/RECORD
